pdfstitcher/__init__.py
pdfstitcher/bug_info.py
pdfstitcher/updater.py
pdfstitcher/utils.py
pdfstitcher/cli/__init__.py
pdfstitcher/cli/__main__.py
pdfstitcher/cli/app.py
pdfstitcher/gui/__init__.py
pdfstitcher/gui/__main__.py
pdfstitcher/gui/app.py
pdfstitcher/gui/dialogs.py
pdfstitcher/gui/io_tab.py
pdfstitcher/gui/layers_tab.py
pdfstitcher/gui/main_frame.py
pdfstitcher/gui/tile_tab.py
pdfstitcher/processing/__init__.py
pdfstitcher/processing/layerfilter.py
pdfstitcher/processing/mainproc.py
pdfstitcher/processing/pagefilter.py
pdfstitcher/processing/pagetiler.py
pdfstitcher/processing/pdf_operators.py
pdfstitcher/processing/procbase.py
pdfstitcher/resources/make_icons.py
pdfstitcher/resources/stitcher-icon.ico
pdfstitcher/resources/locale/cs_CZ/LC_MESSAGES/pdfstitcher.mo
pdfstitcher/resources/locale/cs_CZ/LC_MESSAGES/pdfstitcher.po
pdfstitcher/resources/locale/da/LC_MESSAGES/pdfstitcher.mo
pdfstitcher/resources/locale/da/LC_MESSAGES/pdfstitcher.po
pdfstitcher/resources/locale/de_DE/LC_MESSAGES/pdfstitcher.mo
pdfstitcher/resources/locale/de_DE/LC_MESSAGES/pdfstitcher.po
pdfstitcher/resources/locale/es_ES/LC_MESSAGES/pdfstitcher.mo
pdfstitcher/resources/locale/es_ES/LC_MESSAGES/pdfstitcher.po
pdfstitcher/resources/locale/fr_FR/LC_MESSAGES/pdfstitcher.mo
pdfstitcher/resources/locale/fr_FR/LC_MESSAGES/pdfstitcher.po
pdfstitcher/resources/locale/hi/LC_MESSAGES/pdfstitcher.mo
pdfstitcher/resources/locale/hi/LC_MESSAGES/pdfstitcher.po
pdfstitcher/resources/locale/hu_HU/LC_MESSAGES/pdfstitcher.mo
pdfstitcher/resources/locale/hu_HU/LC_MESSAGES/pdfstitcher.po
pdfstitcher/resources/locale/it/LC_MESSAGES/pdfstitcher.mo
pdfstitcher/resources/locale/it/LC_MESSAGES/pdfstitcher.po
pdfstitcher/resources/locale/nb_NO/LC_MESSAGES/pdfstitcher.mo
pdfstitcher/resources/locale/nb_NO/LC_MESSAGES/pdfstitcher.po
pdfstitcher/resources/locale/nl_NL/LC_MESSAGES/pdfstitcher.mo
pdfstitcher/resources/locale/nl_NL/LC_MESSAGES/pdfstitcher.po
pdfstitcher-1.2.dist-info/LICENSE
pdfstitcher-1.2.dist-info/METADATA
pdfstitcher-1.2.dist-info/WHEEL
pdfstitcher-1.2.dist-info/entry_points.txt
pdfstitcher-1.2.dist-info/top_level.txt
pdfstitcher-1.2.dist-info/RECORD
