Metadata-Version: 2.1
Name: pdfstitcher
Version: 1.2
Summary: The open source PDF stitching software for sewists, by sewists.
Author: Charlotte Curtis
Author-email: c.f.curtis@gmail.com
License: Mozilla Public License Version 2.0
Project-URL: homepage, https://www.pdfstitcher.org/
Project-URL: repository, https://github.com/cfcurtis/pdfstitcher
Keywords: pdf,sewing,utility,stitch,n-up,page imposition
Classifier: Programming Language :: Python :: 3
Classifier: License :: OSI Approved :: Mozilla Public License 2.0 (MPL 2.0)
Classifier: Operating System :: OS Independent
Requires-Python: >=3.8
License-File: LICENSE
Requires-Dist: pikepdf >=9.1.1
Requires-Dist: Babel
Requires-Dist: PyYAML
Requires-Dist: appdirs
Provides-Extra: dev
Requires-Dist: pytest ; extra == 'dev'
Requires-Dist: pytest-cov ; extra == 'dev'
Requires-Dist: pre-commit ; extra == 'dev'
Requires-Dist: black ; extra == 'dev'
Provides-Extra: gui
Requires-Dist: wxPython >=4.2 ; extra == 'gui'
Requires-Dist: requests ; extra == 'gui'
Requires-Dist: pdf-mangler ; extra == 'gui'
Requires-Dist: psutil ; extra == 'gui'
